flight_sql_websocket_proxy/__init__.py
flight_sql_websocket_proxy/client.py
flight_sql_websocket_proxy/config.py
flight_sql_websocket_proxy/constants.py
flight_sql_websocket_proxy/security.py
flight_sql_websocket_proxy/server.py
flight_sql_websocket_proxy/utils.py
flight_sql_websocket_proxy/server_components/__init__.py
flight_sql_websocket_proxy/server_components/common.py
flight_sql_websocket_proxy/server_components/server_class.py
flight_sql_websocket_proxy/server_components/server_client.py
flight_sql_websocket_proxy/server_components/server_query.py
flight_sql_websocket_proxy/setup/__init__.py
flight_sql_websocket_proxy/setup/tls_utilities.py
flight_sql_websocket_proxy-0.0.13.dist-info/licenses/LICENSE
flight_sql_websocket_proxy-0.0.13.dist-info/METADATA
flight_sql_websocket_proxy-0.0.13.dist-info/WHEEL
flight_sql_websocket_proxy-0.0.13.dist-info/entry_points.txt
flight_sql_websocket_proxy-0.0.13.dist-info/top_level.txt
flight_sql_websocket_proxy-0.0.13.dist-info/RECORD
