Metadata-Version: 2.4
Name: flight-sql-websocket-proxy
Version: 0.0.13
Summary: A Python-based Apache Arrow Flight SQL WebSocket Proxy Server
Author-email: Philip Moore <philip@gizmodata.com>
License-Expression: Apache-2.0
Project-URL: Homepage, https://github.com/gizmodata/flight-sql-websocket-proxy
Keywords: arrow,flight,sql,websocket,proxy,server
Classifier: Programming Language :: Python
Classifier: Programming Language :: Python :: 3
Requires-Python: >=3.12
License-File: LICENSE
Requires-Dist: click==8.3.*
Requires-Dist: codetiming==1.4.*
Requires-Dist: munch==4.0.*
Requires-Dist: adbc-driver-flightsql==1.8.*
Requires-Dist: pyarrow==21.0.*
Requires-Dist: python-dateutil==2.9.*
Requires-Dist: pytz==2025.*
Requires-Dist: websockets==15.0.*
Requires-Dist: python-dotenv==1.1.*
Requires-Dist: cryptography==45.0.*
Requires-Dist: requests==2.32.*
Requires-Dist: clerk-backend-api==3.3.*
Requires-Dist: psutil==7.1.*
Provides-Extra: dev
Requires-Dist: bumpver; extra == "dev"
Requires-Dist: pip-tools; extra == "dev"
Requires-Dist: pytest; extra == "dev"
Provides-Extra: client
Requires-Dist: pandas==2.3.*; extra == "client"
Dynamic: license-file
